{
  "entrypoints": [
    "main"
  ],
  "origins": {
    "main": [
      "212",
      "580",
      "909"
    ],
    "runtime~main": [
      "212",
      "909",
      "580"
    ],
    "styles": [
      "16",
      "580",
      "909",
      "212"
    ],
    "common": [
      "212",
      "16"
    ]
  },
  "assets": {
    "16": {
      "js": [
        {
          "file": "assets/js/common.bfe8c5bc.js",
          "hash": "0fe5efb7dc75c148",
          "publicPath": "/assets/js/common.bfe8c5bc.js"
        }
      ]
    },
    "212": {
      "css": [
        {
          "file": "assets/css/styles.253b0847.css",
          "hash": "5f030ba299a45a73",
          "publicPath": "/assets/css/styles.253b0847.css"
        }
      ]
    },
    "580": {
      "js": [
        {
          "file": "assets/js/runtime~main.96fe0c28.js",
          "hash": "14bfd5374ddc6eb7",
          "publicPath": "/assets/js/runtime~main.96fe0c28.js"
        }
      ]
    },
    "909": {
      "js": [
        {
          "file": "assets/js/main.8338c17e.js",
          "hash": "bf233d4d3fdca351",
          "publicPath": "/assets/js/main.8338c17e.js"
        }
      ]
    }
  }
}